{
  "month": "June",
  "month_vi": "Tháng 6",
  "year": 2026,
  "standard_hours_per_month": 192,
  "last_updated": "2026-06-03T13:22:30+07:00",
  "owner": {
    "name": "Quân Hoàng",
    "email": "hoangbinhquan179@gmail.com",
    "account_id": "712020:d8b2807a-adfc-42a8-9ba7-a3e22f01d907"
  },
  "work_schedule": {
    "mon_fri_hours": 8,
    "saturday_hours": 4,
    "sunday_hours": 0,
    "note": "T2-T6=8h, T7 sáng=4h, CN=nghỉ"
  },
  "daily_logs": {
    "2026-06-01": 0,
    "2026-06-02": 57600,
    "2026-06-03": 14400,
    "2026-06-04": 0,
    "2026-06-05": 0,
    "2026-06-06": 0,
    "2026-06-08": 0,
    "2026-06-09": 0,
    "2026-06-10": 0,
    "2026-06-11": 0,
    "2026-06-12": 0,
    "2026-06-13": 0,
    "2026-06-15": 0,
    "2026-06-16": 0,
    "2026-06-17": 0,
    "2026-06-18": 0,
    "2026-06-19": 0,
    "2026-06-20": 0,
    "2026-06-22": 0,
    "2026-06-23": 0,
    "2026-06-24": 0,
    "2026-06-25": 0,
    "2026-06-26": 0,
    "2026-06-27": 0,
    "2026-06-29": 0,
    "2026-06-30": 0
  },
  "tasks": [
    {
      "key": "EXDMS-2635",
      "summary": "[DMS][DEV][BE] Phân giải Người xử lý theo Hierarchy",
      "project": "Extended DMS",
      "issue_type": "Subtask",
      "status": "Done",
      "resolved_date": "2026-06-03",
      "worklog_started": "2026-06-03",
      "time_spent_seconds": 7200,
      "time_spent_display": "2h",
      "url": "https://pvqpm.atlassian.net/browse/EXDMS-2635"
    },
    {
      "key": "EXDMS-2655",
      "summary": "[DMS][GO][BE] Phân quyền org cho admin duyệt đơn",
      "project": "Extended DMS",
      "issue_type": "Subtask",
      "status": "Done",
      "resolved_date": "2026-06-03",
      "worklog_started": "2026-06-03",
      "time_spent_seconds": 7200,
      "time_spent_display": "2h",
      "url": "https://pvqpm.atlassian.net/browse/EXDMS-2655"
    },
    {
      "key": "DMSV2-52",
      "summary": "[LYT-ERP] LYT-106 Cập nhật Swagger / API doc endpoint Outbound",
      "project": "DMS Platform",
      "issue_type": "Sub-task",
      "status": "Done",
      "resolved_date": "2026-06-02",
      "worklog_started": null,
      "time_spent_seconds": 0,
      "time_spent_display": "⚠️ Chưa log",
      "url": "https://pvqpm.atlassian.net/browse/DMSV2-52"
    },
    {
      "key": "EXDMS-2636",
      "summary": "[DMS][DEV][FE] Sinh trạng thái đích danh trên báo cáo",
      "project": "Extended DMS",
      "issue_type": "Subtask",
      "status": "Done",
      "resolved_date": "2026-06-02",
      "worklog_started": "2026-06-02",
      "time_spent_seconds": 7200,
      "time_spent_display": "2h",
      "url": "https://pvqpm.atlassian.net/browse/EXDMS-2636"
    },
    {
      "key": "EXDMS-2632",
      "summary": "[DMS][DEV][BE] Bổ sung các trường người đại diện vào bảng sub_inventories",
      "project": "Extended DMS",
      "issue_type": "Subtask",
      "status": "Done",
      "resolved_date": "2026-06-02",
      "worklog_started": "2026-06-02",
      "time_spent_seconds": 14400,
      "time_spent_display": "4h",
      "url": "https://pvqpm.atlassian.net/browse/EXDMS-2632"
    },
    {
      "key": "EXDMS-2634",
      "summary": "[DMS][DEV][BE] Cập nhật API GET/PUT danh mục Kho Sub",
      "project": "Extended DMS",
      "issue_type": "Subtask",
      "status": "Done",
      "resolved_date": "2026-06-02",
      "worklog_started": "2026-06-02",
      "time_spent_seconds": 7200,
      "time_spent_display": "2h",
      "url": "https://pvqpm.atlassian.net/browse/EXDMS-2634"
    },
    {
      "key": "EXDMS-2626",
      "summary": "[DMS][GO][BE] Thiết kế database, xử lý API đồng bộ & logic Xóa tuyến trạng thái Khách hàng",
      "project": "Extended DMS",
      "issue_type": "Subtask",
      "status": "Done",
      "resolved_date": "2026-06-02",
      "worklog_started": "2026-06-02",
      "time_spent_seconds": 28800,
      "time_spent_display": "8h",
      "url": "https://pvqpm.atlassian.net/browse/EXDMS-2626"
    }
  ]
}
